nsdotpy/__init__.py
nsdotpy/session.py
nsdotpy/valid.py
nsdotpy-2.3.0.dist-info/LICENSE.md
nsdotpy-2.3.0.dist-info/METADATA
nsdotpy-2.3.0.dist-info/WHEEL
nsdotpy-2.3.0.dist-info/RECORD
