Metadata-Version: 2.1
Name: nsdotpy
Version: 2.3.0
Summary: A wrapper around httpx that abstracts away interacting with the HTML nationstates.net site. Focused on legality, correctness, and ease of use.
Home-page: https://github.com/sw33ze/NSDotPy
License: AGPL-3.0-or-later
Author: audrey
Author-email: audreyreal@proton.me
Requires-Python: >=3.10,<3.13
Classifier: License :: OSI Approved :: GNU Affero General Public License v3 or later (AGPLv3+)
Classifier: Programming Language :: Python :: 3
Classifier: Programming Language :: Python :: 3.10
Classifier: Programming Language :: Python :: 3.11
Classifier: Programming Language :: Python :: 3.12
Requires-Dist: beautifulsoup4 (>=4.12.3,<5.0.0)
Requires-Dist: httpx[http2] (>=0.24.0,<0.25.0)
Requires-Dist: keyboard (>=0.13.5,<0.14.0)
Requires-Dist: lxml (>=4.9.4,<5.0.0)
Requires-Dist: python-benedict[parse,xml] (>=0.31.0,<0.32.0)
Project-URL: Repository, https://github.com/sw33ze/NSDotPy
